{
    "00001" : {
        "userId" : "00001" ,
        "userName" : "00001"

    },
    "00003" : {
        "userId" : "00002" ,
        "userName" : "00001"

    },
    "00004" : {
        "userId" : "00004" ,
        "userName" : "00001"

    },
    "00005" : {
        "userId" : "00005" ,
        "userName" : "00001"

    },
    "00006" : {
        "userId" : "00006" ,
        "userName" : "00001"

    },
    "00007" : {
        "userId" : "00007" ,
        "userName" : "00001"

    },
    "00008" : {
        "userId" : "00008" ,
        "userName" : "00001"

    },
    "00009" : {
        "userId" : "00009" ,
        "userName" : "00001"

    },
    "000010" : {
        "userId" : "000010" ,
        "userName" : "00001"

    }
}